di_container/__init__.py
di_container/container.py
di_container-2.1.10.dist-info/LICENSE
di_container-2.1.10.dist-info/METADATA
di_container-2.1.10.dist-info/WHEEL
di_container-2.1.10.dist-info/top_level.txt
di_container-2.1.10.dist-info/RECORD
