Metadata-Version: 2.1
Name: di-container
Version: 2.1.10
Summary: A dependency injection container for Python, using semantics similar to Castle Windsor.
Home-page: https://github.com/eyaldror/di_container
Author: Eyal Dror
License: UNKNOWN
Platform: UNKNOWN
Classifier: Programming Language :: Python :: 3
Classifier: License :: OSI Approved :: MIT License
Classifier: Operating System :: OS Independent
Requires-Python: >=3.5.0
